{
  "date":"Nov 20",
    "matchimg":"https://www.insidesport.in/wp-content/uploads/2022/11/WhatsApp-Image-2022-11-18-at-10.14.51-PM.jpeg?w=690",
    "time":"10:30 PM",
  
  
  "img":"https://3photos6.files.wordpress.com/2022/11/4.gif",
  "link": "https://bit.ly/3TZMDjl",
  "messenger":"no",
  
  
  
  
  
  
  
  
     "freee":"yes",
  "live": [
      {
  "link":"SD 1",
    "livelink":"https://pullalilive.livnvess.com/live/stream-121256_ld.m3u8?auth_key=1668972570-0-0-6403ff238607bcdaa535f9a138162359"
},
     {
  "link":"HD 1",
    "livelink":"https://pullalilive.livnvess.com/live/stream-121256.m3u8?auth_key=1668972570-0-0-a14f8a619b3448ba1ccdf710c63e1626"
}
]
  
  
}
